concern/Concern.arid
concern/Concern.py
concern/__init__.py
concern/getblock.py
concern/util.py
concern/templates/__init__.py
concern/templates/loop.py.aridt
concern/templates/quit.py.aridt
concern/templates/screenrc.aridt
concern/templates/sendblock.py.aridt
concern/templates/session.vim.aridt
Concern-35.dist-info/COPYING
Concern-35.dist-info/METADATA
Concern-35.dist-info/WHEEL
Concern-35.dist-info/entry_points.txt
Concern-35.dist-info/top_level.txt
Concern-35.dist-info/RECORD
