Metadata-Version: 2.1
Name: Concern
Version: 35
Summary: Control pym2149 (via Lurlene) or FoxDot using Vim
Home-page: https://github.com/combatopera/Concern
Author: Andrzej Cichocki
Author-email: 3613868+combatopera@users.noreply.github.com
License-File: COPYING
Requires-Dist: aridity>=84
Requires-Dist: foyndation>=10
Requires-Dist: lagoon>=50
Requires-Dist: timelyOSC>=4
